odoo/addons/l10n_it_reverse_charge/README.rst
odoo/addons/l10n_it_reverse_charge/__init__.py
odoo/addons/l10n_it_reverse_charge/__manifest__.py
odoo/addons/l10n_it_reverse_charge/data/rc_type.xml
odoo/addons/l10n_it_reverse_charge/i18n/am.po
odoo/addons/l10n_it_reverse_charge/i18n/ar.po
odoo/addons/l10n_it_reverse_charge/i18n/bg.po
odoo/addons/l10n_it_reverse_charge/i18n/bs.po
odoo/addons/l10n_it_reverse_charge/i18n/ca.po
odoo/addons/l10n_it_reverse_charge/i18n/cs.po
odoo/addons/l10n_it_reverse_charge/i18n/da.po
odoo/addons/l10n_it_reverse_charge/i18n/de.po
odoo/addons/l10n_it_reverse_charge/i18n/el_GR.po
odoo/addons/l10n_it_reverse_charge/i18n/en_GB.po
odoo/addons/l10n_it_reverse_charge/i18n/es.po
odoo/addons/l10n_it_reverse_charge/i18n/es_AR.po
odoo/addons/l10n_it_reverse_charge/i18n/es_CL.po
odoo/addons/l10n_it_reverse_charge/i18n/es_CO.po
odoo/addons/l10n_it_reverse_charge/i18n/es_CR.po
odoo/addons/l10n_it_reverse_charge/i18n/es_DO.po
odoo/addons/l10n_it_reverse_charge/i18n/es_EC.po
odoo/addons/l10n_it_reverse_charge/i18n/es_ES.po
odoo/addons/l10n_it_reverse_charge/i18n/es_MX.po
odoo/addons/l10n_it_reverse_charge/i18n/es_PE.po
odoo/addons/l10n_it_reverse_charge/i18n/es_PY.po
odoo/addons/l10n_it_reverse_charge/i18n/es_VE.po
odoo/addons/l10n_it_reverse_charge/i18n/et.po
odoo/addons/l10n_it_reverse_charge/i18n/eu.po
odoo/addons/l10n_it_reverse_charge/i18n/fa.po
odoo/addons/l10n_it_reverse_charge/i18n/fi.po
odoo/addons/l10n_it_reverse_charge/i18n/fr.po
odoo/addons/l10n_it_reverse_charge/i18n/fr_CA.po
odoo/addons/l10n_it_reverse_charge/i18n/fr_CH.po
odoo/addons/l10n_it_reverse_charge/i18n/gl.po
odoo/addons/l10n_it_reverse_charge/i18n/gl_ES.po
odoo/addons/l10n_it_reverse_charge/i18n/he.po
odoo/addons/l10n_it_reverse_charge/i18n/hr.po
odoo/addons/l10n_it_reverse_charge/i18n/hr_HR.po
odoo/addons/l10n_it_reverse_charge/i18n/hu.po
odoo/addons/l10n_it_reverse_charge/i18n/id.po
odoo/addons/l10n_it_reverse_charge/i18n/it.po
odoo/addons/l10n_it_reverse_charge/i18n/ja.po
odoo_addon_l10n_it_reverse_charge-16.0.1.0.11.dist-info/METADATA
odoo_addon_l10n_it_reverse_charge-16.0.1.0.11.dist-info/WHEEL
odoo_addon_l10n_it_reverse_charge-16.0.1.0.11.dist-info/top_level.txt
odoo_addon_l10n_it_reverse_charge-16.0.1.0.11.dist-info/RECORD
